ifnumberequals123/__about__.py
ifnumberequals123/__init__.py
ifnumberequals123-0.0.4.dist-info/METADATA
ifnumberequals123-0.0.4.dist-info/WHEEL
ifnumberequals123-0.0.4.dist-info/licenses/LICENSE.txt
ifnumberequals123-0.0.4.dist-info/RECORD
